.coveragerc
.dockerignore
.editorconfig
.env.example
.git/COMMIT_EDITMSG
.git/FETCH_HEAD
.git/HEAD
.git/config
.git/config.worktree
.git/description
.git/hooks/applypatch-msg.sample
.git/hooks/commit-msg.sample
.git/hooks/fsmonitor-watchman.sample
.git/hooks/post-update.sample
.git/hooks/pre-applypatch.sample
.git/hooks/pre-commit.sample
.git/hooks/pre-merge-commit.sample
.git/hooks/pre-push.sample
.git/hooks/pre-rebase.sample
.git/hooks/pre-receive.sample
.git/hooks/prepare-commit-msg.sample
.git/hooks/push-to-checkout.sample
.git/hooks/sendemail-validate.sample
.git/hooks/update.sample
.git/index
.git/info/exclude
.git/logs/HEAD
.git/logs/refs/heads/main
.git/logs/refs/remotes/origin/HEAD
.git/logs/refs/remotes/origin/async-api
.git/logs/refs/remotes/origin/feature/headless-allauth
.git/logs/refs/remotes/origin/main
.git/logs/refs/remotes/origin/qodana-automation-402410151
.git/logs/refs/remotes/origin/webside
.git/objects/0c/9b01da887ea1b7afdc5ccb908c082f7d33db45
.git/objects/30/25a1a0d35ad056512ebac9395f2066247c6f2a
.git/objects/30/9e8581c19f6311468ef7fcfd5ac6c0b0a66782
.git/objects/6d/d4ed851287f6bab2b7ded677b1924ee4d10bf0
.git/objects/d3/81525bf2bdc79cdfd85a96bdf042d24b704c11
.git/objects/df/fb740e254bf0b839256b26fe302d5c3eaaf2c2
.git/objects/pack/pack-6f051234d6ecfe62930542d7c200015dec88797a.idx
.git/objects/pack/pack-6f051234d6ecfe62930542d7c200015dec88797a.pack
.git/objects/pack/pack-6f051234d6ecfe62930542d7c200015dec88797a.rev
.git/refs/heads/main
.git/refs/remotes/origin/HEAD
.git/refs/remotes/origin/async-api
.git/refs/remotes/origin/feature/headless-allauth
.git/refs/remotes/origin/main
.git/refs/remotes/origin/qodana-automation-402410151
.git/refs/remotes/origin/webside
.git/refs/tags/v0.1.0
.git/refs/tags/v0.1.1
.git/refs/tags/v0.10.0
.git/refs/tags/v0.10.1
.git/refs/tags/v0.100.0
.git/refs/tags/v0.101.0
.git/refs/tags/v0.102.0
.git/refs/tags/v0.102.1
.git/refs/tags/v0.103.0
.git/refs/tags/v0.104.0
.git/refs/tags/v0.104.1
.git/refs/tags/v0.105.0
grooveshop_django_api-1.0.0.dist-info/LICENSE.md
grooveshop_django_api-1.0.0.dist-info/METADATA
grooveshop_django_api-1.0.0.dist-info/WHEEL
grooveshop_django_api-1.0.0.dist-info/RECORD
