Metadata-Version: 2.3
Name: grooveshop-django-api
Version: 1.0.0
Summary: GrooveShop Django Backend
License: MIT
Author: Vasilis Totskas
Author-email: vassilistotskas@msn.com
Requires-Python: >=3.11,<4.0.0
Classifier: License :: OSI Approved :: MIT License
Classifier: Programming Language :: Python :: 3
Classifier: Programming Language :: Python :: 3.11
Classifier: Programming Language :: Python :: 3.12
Classifier: Programming Language :: Python :: 3.13
Requires-Dist: asgiref (==3.8.1)
Requires-Dist: boto3 (==1.38.4)
Requires-Dist: celery[redis] (>=5.5.2,<6.0.0)
Requires-Dist: channels (==4.2.2)
Requires-Dist: channels-redis (==4.2.1)
Requires-Dist: charset_normalizer (==3.4.1)
Requires-Dist: cryptography (==44.0.2)
Requires-Dist: django (==5.2)
Requires-Dist: django-admin-thumbnails (==0.2.9)
Requires-Dist: django-allauth (==65.7.0)
Requires-Dist: django-celery-beat (==2.8.0)
Requires-Dist: django-celery-results (==2.6.0)
Requires-Dist: django-cors-headers (==4.7.0)
Requires-Dist: django-csp (==4.0b7)
Requires-Dist: django-dbbackup (==4.2.1)
Requires-Dist: django-extra-settings (==0.14.0)
Requires-Dist: django-filter (==25.1)
Requires-Dist: django-money (==3.5.4)
Requires-Dist: django-mptt (==0.17.0)
Requires-Dist: django-parler (==2.3.0)
Requires-Dist: django-parler-rest (==2.2.0)
Requires-Dist: django-phonenumber-field (==8.1.0)
Requires-Dist: django-rest-knox (==5.0.2)
Requires-Dist: django-rosetta (==0.10.2)
Requires-Dist: django-simple-history (==3.8.0)
Requires-Dist: django-storages (==1.14.6)
Requires-Dist: django-tinymce (==4.1.0)
Requires-Dist: django-unfold (==0.55.3)
Requires-Dist: djangorestframework (==3.16.0)
Requires-Dist: djangorestframework-camel-case (==1.4.2)
Requires-Dist: drf-spectacular (==0.28.0)
Requires-Dist: fido2 (==1.2.0)
Requires-Dist: flower (==2.0.1)
Requires-Dist: gunicorn (==23.0.0)
Requires-Dist: importlib-resources (==6.5.2)
Requires-Dist: measurement (==3.2.2)
Requires-Dist: meilisearch (==0.34.1)
Requires-Dist: phonenumbers (==9.0.4)
Requires-Dist: pillow (==11.2.1)
Requires-Dist: psycopg[binary,pool] (==3.2.6)
Requires-Dist: python-dotenv (==1.1.0)
Requires-Dist: qrcode (==8.1)
Requires-Dist: urllib3 (==2.4.0)
Requires-Dist: uvicorn (==0.34.2)
Project-URL: Repository, https://github.com/vasilistotskas/grooveshop-django-api
